extr/__init__.py
extr/models.py
extr/entities/__init__.py
extr/entities/annotator.py
extr/entities/context.py
extr/entities/extractor.py
extr/entities/factories.py
extr/entities/linkers.py
extr/entities/viewers/__init__.py
extr/entities/viewers/html.py
extr/pipelines/__init__.py
extr/pipelines/pipes.py
extr/regexes/__init__.py
extr/regexes/regex.py
extr/relations/__init__.py
extr/relations/annotator.py
extr/relations/extractor.py
extr/relations/label_builder.py
extr/relations/viewers/__init__.py
extr/relations/viewers/html.py
extr/tokenizers/__init__.py
extr/tokenizers/tokenizer.py
extr/utils/__init__.py
extr/utils/iterutils.py
extr/utils/query.py
extr-0.0.44.dist-info/LICENSE
extr-0.0.44.dist-info/METADATA
extr-0.0.44.dist-info/WHEEL
extr-0.0.44.dist-info/top_level.txt
extr-0.0.44.dist-info/RECORD
