Metadata-Version: 2.1
Name: extr
Version: 0.0.44
Summary: Named Entity Recognition (NER) and Relation Extraction (RE) library using Regular Expressions
Home-page: https://github.com/dpasse/extr
License: UNKNOWN
Keywords: Named Entity Recognition,Relation Extraction,Entity Linking,NER,RE,NLP
Platform: UNKNOWN
